c3d/__init__.py
c3d/c3d.py
c3d/scripts/__init__.py
c3d/scripts/c3d2csv.py
c3d/scripts/c3d2npz.py
c3d/scripts/c3d_metadata.py
c3d/scripts/c3d_viewer.py
c3d-0.5.1.dist-info/entry_points.txt
c3d-0.5.1.dist-info/LICENSE
c3d-0.5.1.dist-info/WHEEL
c3d-0.5.1.dist-info/METADATA
c3d-0.5.1.dist-info/RECORD
