Metadata-Version: 2.1
Name: c3d
Version: 0.5.1
Summary: A library for manipulating C3D binary files
Home-page: https://github.com/EmbodiedCognition/py-c3d
License: MIT
Keywords: c3d,motion-capture
Author: UT Vision, Cognition, and Action Lab
Maintainer: Leif Johnson
Maintainer-email: leif@cs.utexas.edu
Requires-Python: >=3.7,<4.0
Classifier: Intended Audience :: Science/Research
Classifier: License :: OSI Approved :: MIT License
Classifier: Operating System :: OS Independent
Classifier: Programming Language :: Python :: 3
Classifier: Programming Language :: Python :: 3.7
Classifier: Programming Language :: Python :: 3.8
Classifier: Programming Language :: Python :: 3.9
Classifier: Topic :: Scientific/Engineering
Provides-Extra: gui
Requires-Dist: numpy (>=1,<2)
Requires-Dist: pyglet (>=1.5.21,<2.0.0); extra == "gui"
Project-URL: Repository, https://github.com/EmbodiedCognition/py-c3d
